{"film_name": "阿飞正传", "film_number": "10053", "film_intro": "故事以六十年代初期为背景，折射的却是90年代人们疲惫的灵魂。阿飞(张国荣)是上海移民，他从未见过生母，自小由养母养大，因此长大后他对生命中遇到的每一个女人都冷酷无情。放荡不羁的他先后与售票员苏丽珍(张曼玉)和舞女咪咪(刘嘉玲)同居，但后来又相继抛弃了她们。阿飞决计找到生母，为此他只身前往南洋。一直暗恋苏丽珍的警察(刘德华)目睹了苏丽珍与阿飞的决裂后，决定改行去跑船。在菲律宾，他又见到了阿飞，此时的阿飞已在一场欧斗中身负重伤。他守着阿飞死在一列返乡的火车上。", "film_year": "1990", "actor": ["张国荣", "张曼玉", "刘德华", "刘嘉玲", "张学友", "潘迪华", "梁朝伟", "Danilo Antunes", "Hung Mei-Mei", "Ling-Hung Ling"], "commit": ["其实我们都以为自己是那只爱飞的鸟。", "《阿飞正传》是我标的第236个豆瓣250，越往后看，越觉得250是一个大众审美标准，我不喜欢大多数250的电影，或者说不那么喜欢，但是我说一个东西不好之前我得看过才说不好。当然这不是说阿飞，二十年前我第一次看阿飞正传的时候，很装逼的觉得有自己的影子，现在看来，只是我年轻的时候我们都放荡而已，凭张国荣和刘嘉玲的两段年代感极强的舞蹈本片该五星，但是考虑到我不太想看第三遍了，四星吧，时光给九分", "真的是现在才看", "这个世界真的有一种鸟，她没有脚，她不停的飞。她爱了太多人，自己都不知道到底在爱谁。她没有家，随时都能出发去新城市生活。她颓废又积极，温柔又阴暗，脆弱又倔强。到最后只道是行为乖癖性乖张，哪管世人诽谤！", "给哥哥配戏"]}