{"film_name": "巴伦", "film_number": "10180", "film_intro": "阿富汗人在伊朗往往从事着最低贱的工作，纳夫就是一位在德黑兰建筑工地出卖廉价劳动力的阿富汗工人。在一次事故中，他摔断了腿，失去了继续干活的能力。为了维持生活，他只能让儿子莱特来顶替自己的工作。但莱特身体瘦弱，无法胜任繁重的工地劳动，工头便安排他负责炊事工作。被顶替掉的炊事负责人拉蒂夫非常恼火，不断给莱特制造麻烦，直至一天他发现了一个惊人的秘密：莱特是女扮男装，她原来的名字叫巴伦。拉蒂夫慢慢喜欢上了巴伦，他不仅为之保守秘密，更想尽办法帮助巴伦度过生活上的难关。纳夫一家最终还是决定离开伊朗，在送行的一刻，巴伦感受到了拉蒂夫的爱意，摘下了她的面纱回应了拉蒂夫的爱。", "film_year": "2001", "actor": ["Hossein Abedini", "Zahra Bahrami", "默罕默德·阿米尔·..", "Hossein Mahjoub", "Abbas Rahimi", "Gholam Ali Bakhshi", "Jafar Tawakoli", "Yadollah Hedayati", "Parviz Larijani", "Mahmoud Behraznia"], "commit": ["工地苦力难民暗恋护花使者为爱痴狂", "马基德·马基迪不愧是得奖常胜军，又是超级票房保证的伊朗之光。镜头再次对准了底层的劳动人民，生存环境的恶劣更能彰显人性本善，女扮男装的姑娘和一往情深的小伙儿，爱情是不分富贵贫穷的，但付出也不一定会有回报，单纯美好的感情真是太美好了。", "为爱痴狂，放下自我的身份，只为那背后的一眼。", "手法特别写实，但叙事顺畅毫不拖沓。镜头语言强大到就像看小说时能从字里行间读出意思一样，让观者也体会到作品饱含的痛惜与深情，感受到创作者对战火的控诉，动荡的时局让人流离失所，生活困苦，丧失尊严。可即便如此生活还是给人留下些珍贵的东西，给人以生的希望", "导演很细心，前面铺垫出男主是个年轻冲动做事不计后果的人，因此后面的发展才不觉得突兀。以及比《山楂树之恋》纯情多了……20161005"]}