{"film_name": "巴士站", "film_number": "10184", "film_intro": "Jae-seop(金泰佑)已经三十二岁的年纪了，却还在一家私立学校里当讲师，工作生活简单平淡，感情上他却对旧日同学念念不忘。班里十七岁的So-hee(KIM Min-jeong)吸引了他的注意，她是一个刚刚升入高中的学生，但是她却有着超越年龄的成熟稳重，白天她是再校的高中女生，夜晚她却是风情万种的交际花，为了钱她沦落风尘，后来还怀上了不知是哪位客人的孩子。Jae-seop与So-hee之间产生了暧昧的情感，两人相互吸引且彼此之间的关系越发的亲密，可是两人年纪的差异加上身份的悬殊让他们心理上都承受了很大的压力，So-hee就像巴士一样每天在公路上停停走走，而Jae-seop就像等在巴士车站的人，他只能等待着So-hee不定时的到来……两个人之间能否有美丽的未来？", "film_year": "2002", "actor": ["金泰宇", "金敏贞", "郑太勋", "朴智娥", "尹珍瑞", "Kong-ju Han", "Ye-ryeong Kim", "崔般若", "郑京虎"], "commit": ["我看港片，也看韩片，我看欧片，也看美片，我看商业片，也看文艺片，我看恐怖片，也看科幻片。这部电影，对于性子急的人，还是别看了，浪费时间，浪费生命。比起电影，电影原声更好听，这是后话。金泰宇是一个喜欢演文艺电影的文艺控演员，中国很缺这样的演员。我是一个喜欢看文艺电影的文艺控影迷，仅此而已。这部电影拍得很细腻，因为是女导演拍的。这部电影还玩了几次小结构，挺有意思的。对于快进看完此片的人，建议去看富春山居图，估计不会快进。", "故事挺好的，怎么拍成这样", "我觉得实在是慢得有点矫情了，受不了了。。。失望", "如果想看无奈这种氛围，建议观看这部电影。想看剧情则需绕道直行。但我敢保证，影片中男猪这种寂寥的生活状态拍的很真切~没看完，因为优酷花屏了~", "三十二岁的Jae-seop(金泰佑) 在一间私立大学里任职学院讲师。对他而言，生活虽然是简单，但他仍未能忘记其日的情人兼同僚。当感到自己生活空虚时，便遇见了她——十七岁的So-hee(KIM Min-jeong)。"]}