{"film_name": "飞龙再生", "film_number": "10571", "film_intro": "\"一直以来，爱尔兰流传着一个传说：只要得到\"\"再生龙章\"\"的再生力量，便会变成永远不灭的“不死人”。神秘华籍小孩Jai拥有这项特异功能，于是国际人蛇集团主脑\"\"蛇魔\"\"(祖利安辛斯饰)千方百计要将其绑架。其手下李斯(黄秋生饰)更与香港特警阿狄(成龙饰)两度交锋，最终掳走Jai。阿狄远赴爱尔兰追捕李斯，在前任女友妮歌(嘉丽科兰妮饰)的穿针引线下，到英国特务屈逊(李伊云士饰)家拜访，认识了其太太夏洛(钟丽缇饰)。阿狄与屈逊两人冰释前嫌再度携手合作。翌日，在混战中为了保护Jai，阿狄不幸身亡，正当大家悲伤之际，另一个阿狄却忽然出现，原来Jai身上的龙章放射出的光芒让他变成了“不死人”。蛇魔欲继续绑架Jai，妮歌为安全计，将Jai暂保护于自己家中，可惜\"\"的党羽们仍然追踪而至，并快阿狄一步，用直升机将掳去。阿狄、妮歌与屈逊为救Jai及彻底剿灭“蛇魔”，决定勇闯古堡巢穴，并与“蛇魔”正面交锋原来，而此时\"\"蛇魔\"\"已经夺去Jai的\"\"龙章\"\"，掌握了神秘的再生力量，变成了“不死人”，一场恶仗即将展开。  \"", "film_year": "2003", "actor": ["成龙", "黄秋生", "钟丽缇", "李·伊万斯", "克莱尔·弗兰妮", "朱利安·山德斯", "约翰·里斯-戴维斯", "Johann Myers", "Alex Bao", "刘兆铭"], "commit": ["一部令人失望的成龙，拥有超能力的成龙令人提不起兴趣，故事则是照搬尖峰时刻，但效果却没有黑人兄弟好，难怪这部电影关注度这么低", "怎么感觉想当年都没宣传过的电影。成龙在当时去好莱坞出了不少的片子好像在国内都没怎么引进。当然以本片的质量来说，没引进也没什么可惜，确实是在平均水平以下。剧情简单，动作戏也是大量威亚，特效十分一般。", "03年成功还能打，却拍出这么粗制滥造的电影", "记得女主角的艳丽", "成龙拍过很多部这种伪好莱坞大片，或许是为了迎合外国观众的口味成龙改变了自己的风格结果片子出来给人的感觉就是粗制滥造，而且特技的应用让人感觉成龙不行了，这个片子算是败笔"]}