{"film_name": "一一", "film_number": "12428", "film_intro": "NJ（吴念真 饰）是个很有原则的生意人，同妻子敏敏（金燕玲 饰）、女儿婷婷、儿子洋洋以及外婆住在台北。小舅子的一场麻烦婚礼过后，因为外婆突然中风昏迷，他迎来更加混乱的日子。 一家人里，似乎只有洋洋没有烦恼，他平静地用照相机拍着各种人的背面，帮他们长出另一双眼睛。", "film_year": "2000", "actor": ["吴念真", "金燕玲", "张洋洋", "林孟瑾", "陈以文", "柯宇纶", "Kelly Lee", "陈希圣", "Su-Yun Ko", "Pang Chang Yu"], "commit": ["婚礼，葬礼，出生，死亡，重聚，分离……时间一直向前走，人生仿佛是轮回，每一个下一秒的我们，都变老了。", "完全没有办法融入进去，感觉用现在的眼光看像是把6集的迷你剧合并成一部电影出来放。故事的话，就是普通家庭剧的故事，不管是冲突还是人物都是非常常见的内容。演技的话也没有什么值得称道的地方，画面更是没有什么讲究，感觉是完全诠释了中庸的片子，真的不明白为什么能被捧那么高，看看评论好像几乎每个人都能从里面看到什么。就像电影里说的，如果电影拍的和普通生活一样，那还看电影干嘛呢？唯一的亮点真的只有洋洋了，小孩的视角的台词和故事不错", "几近冰冷般淡然的镜头，让每个人不分出身地皱着眉头活在了他人的世界，却又发现天下其实是同一个世界。", "A One and a Two", "“如果电影都是过生活，那我们就过生活就好了”，这部电影真的是过生活……"]}