{"film_name": "一夜风流", "film_number": "12427", "film_intro": "这部爱情喜剧发生在一个逃出家门的富家女和一个报纸记者之间。富家千金艾丽迷上飞行员金，因遭父亲反对而离家出走，在长途巴士上遇上丢了工作的记者彼得，艾丽为了搭便车愿意卖弄性感，而彼得跟她同房却要用毯子隔开。艾丽的父亲聘请私家侦探追查女儿行踪，并在报上刊登消息，彼得因而发现艾丽的身份。为了掌握住这条独家新闻，彼得沿途对艾丽多方照顾。两人在相处中产生了恋情，后来经过一番周折，有情人终成眷属。", "film_year": "1934", "actor": ["克拉克·盖博", "克劳黛·考尔白", "沃尔特·康诺利", "Roscoe Karns", "Jameson Thomas", "艾伦·海尔", "Arthur Hoyt", "Blanche Friderici", "Charles C. Wilson", "Ernie Adams"], "commit": ["通过DVD来了解的一部爱情轻喜剧，里面的打车、扛美女等桥段被后来很多电影模仿，最后吹小号放帘子也是记忆深刻。", "作为一部1934年的电影实在太牛逼了，同时四条眉毛的盖博这部里实在太陆小凤了，怀疑古龙是不是看的这个写的。", "型男靓女欢喜冤家式爱情偶像剧的鼻祖片。没想到出世即巅峰，不仅书写了类型教科书的范本还树立了一座大满贯的影史丰碑。从人设建立到台词撰写，人物间的身份错位与俏皮话的冷嘲热讽都设计得精妙绝伦。再从露腿拦车到吹号倒墙，众多的经典桥段亦被后世模仿致敬，经久不衰且难以逾越。纵观全片，完美的剧本结构，完美的节奏处理，完美的演绎方式。毫无矫揉造作和脱离现实之感，妙到毫巅，无可挑剔。是一部完美到无论放在任何时代都熠熠生辉的伟大作品。", "最初的套路电影", "好甜！好虐！故事好符合逻辑！人物好可爱！为什么现在没有这么好看的爱情电影！"]}