{"film_name": "与狼共舞", "film_number": "13353", "film_intro": "影片从一个为苏族印第安人翻案的观点，描述美国白人军官邓巴在南北战争之后自愿到西部前线驻守，结果跟语言不通文化不同的苏族战士交上了朋友，双方时相往还。后来前往当地的白人军队反而将他视为叛徒，对他暴力相向。邓巴从此以身为白人为耻，彻底投向苏族人的阵营，并坚持自己的名字叫“与狼共舞”。", "film_year": "1990", "actor": ["凯文·科斯特纳", "玛丽·麦克唐纳", "格雷厄姆·格林", "罗德尼·格兰特", "弗洛伊德·怀斯特曼", "坦图·卡丁诺", "Robert Pastorelli", "查尔斯·罗基特", "莫里·柴金", "Jimmy Herman"], "commit": ["不同文明之间的交流明明可以不通过杀戮来解决，但太多人都以武力征伐为手段，印第安人所谓的凶残也不过是因为不了解和自保。后半段男主接连失去心爱的马和狼朋友太虐了。Kevin Costner又帅又有才，不过可能就差点运气，导演处女座即巅峰，这样一部十分恢弘的史诗片之后时运急转，好可惜……", "画面", "有点儿…慢…", "片子本身不差，文化交流这个切入点也不错。但是那啥", "史诗，优美，浪漫，悲怆"]}