{"film_name": "尽善尽美", "film_number": "14254", "film_intro": "梅尔文·乌代是全世界最讨人嫌的人。他神经兮兮，说话刻薄，自私自利，浑身都是怪僻，连去餐馆吃饭都自带塑料餐具。就这样一个老头居然写了62部言情小说，而在生活中要他说别人一句好话简直会要他的命，说“我爱你”更是比登天还难。", "film_year": "1997", "actor": ["杰克·尼科尔森", "海伦·亨特", "格雷戈·金尼尔", "小库珀·古丁", "斯基特·乌尔里奇", "雪莉·奈特", "雅德丽·史密斯", "米西·派勒", "沙恩·布莱克", "彼得·雅各布森"], "commit": ["一个有洁癖的作家，有点可爱很毒舌，其实内心很好人，但那眼眉挑起，还是忍不住想起闪灵的画面，女主角很有魅力，聪明善良温柔，但男主角和女主角的妈妈更像一对，最后发成爱情有点老套", "海报10分，影片7-8分。杰克米克尔森的表演太棒了。", "梅尔文这个角色看到了中老年谢尔顿的影子，强迫症、嘴毒心善、不喜欢改变，哈哈，很有趣，话说美国90年代出的大多是精品啊，好怀念！", "若你喜欢怪人 其实我也很美", "大概是海伦最不讨喜的角色之一。"]}