{"film_name": "一条安达鲁狗", "film_number": "18852", "film_intro": "本片是电影史上一部超现实主义的划时代名作，由达利和布努艾尔共同编写，两人都客串了角色。第一段：一个年轻女子安稳地坐着，布努艾尔用刀片把她的眼睛割开。接着是一段纪录片，描述一段梦境，包括蚂蚁、盒子，以及带有弗洛伊德色彩的内容。这是两个最具想像力的西班牙艺术家的奇思异想。", "film_year": "1929", "actor": ["路易斯·布努埃尔", "萨尔瓦多·达利", "Simone Mareuil", "Robert Hommet", "Marval", "Fano Messan", "Pierre Batcheff", "Jaume Miravitlles"], "commit": ["毫无逻辑叙事 衣服箱子贯穿始终", "纪念路易斯·布努埃尔诞辰120周年！", "超现实主义电影的经典代表。各种隐晦深邃富含隐喻的情节，比如用刀割眼，爬满蚂蚁的手，街上的断手等等。影片几乎没什么剧情可言，而是一个个不同的片段跳脱的衔接在一起，看的人云里雾里，看不懂", "1929年，超现实主义，卢米埃尔、达利制作并参演，拼贴作品之母。终于看了这部tag齐片长的传说中影史级上古影片。割眼、手掌爬蚂蚁几个镜头确实经典，但叙事也实在是跳跃，隐喻象征又太深，有点拿VUE剪10秒微信可上传影片的感觉。还好片长只有16分钟，可以毫不费力的多刷。", "切割眼球那个镜头效果真是惊人，我立即就把舍友喊过来看，感觉应该用无政府主义＋弗洛伊德来解答这部电影，应该讲的一个人受各种情况影响下的成长抗争。"]}