{"film_name": "梦想奔驰", "film_number": "25172", "film_intro": "本·科瑞恩曾是一名十分出色的骑师，可随着年华流逝，如今的本只能靠给别人驯马来打发日子，昔日的才华和荣耀渐渐在平淡的生活中褪色。桑亚曾经是一匹非常优秀的赛马，可在一次意外中，他不幸跌断了一条腿，赛场生涯也似乎划上了句号。不能再参加比赛的桑亚对于本·科瑞恩的老板来说无异于一个废物，于是，它被当做解雇费，伴随着一纸解雇书，一起递到了本的手中。小天使一般可爱的凯尔是本的小女儿，她非常喜欢父亲带回来的桑亚，并很快和它成为了好朋友。凯尔虽然年纪不大，却是一个很有主意的小姑娘，她偷偷制定了一个计划，来帮助失意的父亲和可爱的新朋友：让本带着桑亚赢得今年比赛的冠军！一个中年危机的父亲，一匹风光不再的赛马，加上人小鬼大的女儿，他们共同的努力，到底能不能完成这个美好的梦想，重现往日的辉煌，重获生活的信心呢？", "film_year": "2005", "actor": ["库尔特·拉塞尔", "达科塔·范宁", "克里斯·克里斯托佛森", "伊丽莎白·苏", "大卫·摩斯", "弗莱迪·罗德里格兹", "路易斯·古兹曼", "奥德·菲尔", "Ken Howard", "Holmes Osborne"], "commit": ["现在已经很难被这类型家庭片所感染了，一切看似都很美好，但却离现实很远，最终还是被赢得赛马奖金的那份喜悦而共鸣", "很好看，可以再看", "不感兴趣", "你愿意为你的梦想押上多少赌注？倾其所有，甚至更多。你愿意成为谁的国王？我不愿意成为国王，我只愿意为你加冕。你知道那个你一直没有做完的梦的结局吗？我一直到最后一刻才知道，那就是我最终实现了那个我曾经一直向往的梦。你愿意……为你，我愿意！", "范宁太青涩，小孩子办出来的成熟。"]}