{"film_name": "我们不是天使", "film_number": "30278", "film_intro": "约瑟夫、朱丽丝和阿尔伯特从恶魔岛的监狱里逃跑出来，他们在一个港口闲荡，等着一条船来把他们载走，在这期间，他们决定从一家商店里偷一些东西出来，以便在路上使用，于是，他们想方设法让那个店主聘请他们去为他修理屋顶。在屋顶上，他们就能窥见这一家人的生活了，然后再找到机会下手行窃。依莎贝尔是这个家庭中的一个女儿，今年刚满十八岁，还没有出嫁，而且她正在渴望她的旧日情人保尔，保尔这时已去巴黎。依莎贝尔的父亲菲利科斯很害怕他的表兄安德烈抢占他的商店。过了一段时间，保尔和安德烈一起回到了这个岛上，他们并没有受到欢迎。而那三个修理屋顶的窃贼还未找到下手的时机……", "film_year": "1955", "actor": ["亨弗莱·鲍嘉", "奥尔多·雷", "彼德·乌斯蒂诺夫", "琼·贝内特", "巴兹尔·雷斯伯恩", "Leo G. Carroll", "John Baer", "格洛瑞亚·陶伯特", "Lea Penman", "约翰·史密斯"], "commit": ["我们不是天使真的跪蛔不错,值得一看", "到这里才发现，那个小胖子是年轻时的彼得"]}